<song>
<title>022a</title>
<source>#TavaPatveruma,#022a</source>
<tags>christian</tags>
<narrator></narrator>
<musicBy>anon</musicBy>
<lyricsBy>anon</lyricsBy>
<genre>1B</genre>
<ref></ref>
<lyrics># Visusvēto Sakramentu godbijīgi pielūdzam, \\ Maizes zīmēs klātesošo Kungu Dievu slavējam \\ ticībā un paļāvībā Viņa vārdam svētajam. 
# Dievam Tēvam, Dievam Dēlam lai ir slava mūžīga \\ debesīs un visā zemē no ikvienas radības. \\ Garam Svētajam lai vienmēr pielūgsme ir līdzīga. Amen. 
&lt;em&gt; Priesteris: Dievs, Tu esi mums dāvājis debesu maizi. &lt;/em&gt; \\
&lt;em&gt; Visi: &lt;/em&gt; Tā nes mums Tavu žēlastību. \\
&lt;em&gt; Priesteris: Lūgsimies... &lt;/em&gt; \\
&lt;em&gt; Visi: &lt;/em&gt; Amen.</lyrics>
</song>