<song>
<title>060</title>
<source>#TavaPatveruma,#060</source>
<tags>christian</tags>
<narrator></narrator>
<musicBy>anon</musicBy>
<lyricsBy>anon</lyricsBy>
<genre>1B</genre>
<ref></ref>
<lyrics># Dievs, mēs Tevi slavējam, Kungs, mēs teicam Tavu spēku: \\ jo Tu valdi pasauli, savām rokām celto ēku. \\ Laiki iet un dienas skrien, Pavēlnieks Tu esi viens. (2x) 
# Eņģeļi un cilvēki, ko Tu debess laimei lēmis, \\ dod Tev godu augstāko, redzot to, ko esi cēlis. \\ Tikai Tu, Kungs, esi svēts un kas Tevis izvēlēts. (2x) 
# Tēvs, kas esi debesīs, visu lietu pirmais sākums: \\ &quot;Notiek vienmēr lai Tavs prāts!&quot; - tāds ir Tavu bērnu lūgums. \\ Savā dzīvē katru dien' mēs Tev kalposim arvien. (2x) 
# Tu kā saule debesīs mūsu dzīvē gaismu rādi; \\ un caur dzīves grūtībām mūs pie sevis tuvāk vadi, \\ lai mēs Tavā valstībā satiktos reiz mūžībā, (2x) 
# Dievs, mēs Tevi slavējam, Radītāju, savu Tēvu; \\ mīlēt Tevi nebeidzam, žēlastībā smeļot  spēku. \\ Savu dzīvi veltījam tikai Tev mēs vienīgam. (2x)</lyrics>
</song>