<song>
<title>144</title>
<source>#TavaPatveruma,#144</source>
<tags>christian</tags>
<narrator></narrator>
<musicBy>anon</musicBy>
<lyricsBy>anon</lyricsBy>
<genre>1B</genre>
<ref></ref>
<lyrics># Dieva mīlestība nekad nevar beigties, nekad nevar beigties, nekad nebeigsies. 
&lt;em&gt; Allelu - alleluja, allelu - alleluja, allelu - alleluja, alleluja! &lt;/em&gt;
# Svētā Gara gaisma nekad nevar beigties, nekad nevar beigties, nekad nebeigsies. 
# Dzīve ar Jēzu nekad nevar beigties, nekad nevar beigties, nekad nebeigsies. 
# Mūžīgā dzīve nekad nevar beigties, nekad nevar beigties, nekad nebeigsies. 
# Dzīvības avots nekad nevar beigties, nekad nevar beigties, nekad nebeigsies. 
# Prieks mūsu sirdīs nekad nevar beigties, nekad nevar beigties, nekad nebeigsies. 
# Miers mūsu sirdīs nekad nevar beigties, nekad nevar beigties, nekad nebeigsies. 
# Tuvākmīlestība nekad nevar beigties, nekad nevar beigties, nekad nebeigsies. 
# Šis svētceļojums nekad nevar beigties, nekad nevar beigties, nekad nebeigsies.</lyrics>
</song>