<song>

<title>sika, maza es gulēju šūpolīša dibinā</title>
<sources>
<source label='FkLaiva'/>
</sources>
<tags>Šūpuļdziesma</tags>
<narrator>Marija Ezeriņa Madonas Saikavā, dz. 1885 g.; pier. E. Melngailis 1924 g. &quot;B.dz. &quot;141</narrator>
<musicBy></musicBy>
<lyricsBy></lyricsBy>
<genre>1B</genre>
<ref></ref>

<lyrics>
# Sīka, maza es gulēju šūpolīšu dibinā! Aijā, aijā, aijajā, šūpolīša dibinā.
# Jau tautiņu kumeliņi mauru mina pagalmā.
# Dziedi skaņi, mazmeitiņa, gara meža maliņā,
# Lai sķiet tautas lielu meitu, lai segloja kumeliņ's.
# Mazajāmi meitiņāmi vējiņš matus plivināj'.
# Vai tādēļi plivināja, ka tās bēdu nezināj'?
# Šņorē mani māmuliņa ar sudraba prievietiņ',
# Lai es augu tieva, gara bandenieka līgaviņ'.
</lyrics>
</song>