<song>
<title>Veļos mani vadīdami</title>
<sources>
<source label='FkLaiva'/>
</sources>
<tags>bēru</tags>
<narrator>Minna Pusburniece Jēkabpils Zasā , &quot;B.b.dz.&quot;90 </narrator>
<musicBy></musicBy>
<lyricsBy></lyricsBy>
<genre>1B</genre>
<ref></ref>

<lyrics>
# Veļos mani vadīdami, nejūdziet baltus zirgus; veļos mani vadīdami, nejūdzati baltus zirgus.\\
Tālu spīdi balti zirgi gauži raud palicēji.
# Gauži kokles noskanēja, vēl gaužāk stabulītes;\\
Gauži tēva noraudāju, vēl gauzāk māmuliņas.


# Man māmiņa piesacīja: šonakt guni neapdzēs,\\
Lai celiņis gaiši spīd, pie Dieviņa piejot.
# Vaļā logi, vaļā durvis, kad es eimu pie Dieviņ',\\
Lai tā mana dvēselīte tumsumāi nemaldās.
# Kas var zvaigznes izskaitīt, kas Mēnesi aiztecēt,\\
Kas var manu dvēselīti pie Dieviņa aizrunāt?
# Skaisti mani pavadiet, viegli mani viziniet - \\
Pār baltām smiltiņām, zaļajāmi skujiņām. 

</lyrics>
</song>