<song>
<title>Visu gadu dziesmas krāju</title>
<sources>
<!--<source label=''/>-->
</sources>
<tags>ligodziesma</tags>
<narrator></narrator>
<musicBy></musicBy>
<lyricsBy></lyricsBy>
<genre></genre>
<ref></ref>
<lyrics># Visu gadu dziesmas krāju, Jāņu dienu gaidīdama;
# Nu atnāca Jāņu diena, nu dziesmiņas jāizdzieda.
# Visu gadu dziesmas krāju sudrabiņa vācelē. 
# Pašā Jāņu vakarā izbārstīju pagalmā.
# Visu gadu Jāni gaidu, nevarēju sagaidīt; 
# Nu es viņu sagaidīju pašā Jāņu vakarā. 
# Pa gadskārtu Jānīts nāca savus bērnus apraudzīt. 
# Sienam sieru, darām alu, kur Jānīti pamielot. 
# Jāņa māte sieru sēja deviņiem stūrīšiem;
# Šim stūrīts, tam stūrīts, Jānīšam viducīts.
# Simtu cepu kukulīšus, Zāļu dienu gaidīdama;
# Simtiņš nāca danču bērnu, zāļu dienas vakarā. 
# Līsti, lietiņ, citu dienu, nelīst' Jāņu vakarāi!
# Salīs manas Jāņu zāles, salīs manas papardītes.
# Koši, koši, jauki, jauki, ka Dievs deva Jāņu dienu:
# Dzied putniņi, dzied ganiņi, Jāņu bērni gavilēja.</lyrics>
</song>